Workbook

Sheet Instructions
A1: TALENT REVIEW WORKBOOK — USER GUIDE
A3: Purpose
A4: This workbook supports the annual / quarterly talent review process: assess employees, place them on the 9-box, plan succession for critical roles, track individual development plans, and provide HRBP-ready metrics.
A6: Sheet Overview
A7: Sheet | B7: Description
A8: Instructions | B8: This guide (you are here).
A9: Talent Review | B9: Master list of employees with Performance (1-5), Potential (1-5), Flight Risk, Readiness, strengths, development areas, and aspirations. 9-Box Position is calculated automatically.
A10: 9-Box Matrix | B10: Visual 3×3 grid of Performance × Potential with counts and employee lists. Distribution summary included.
A11: Succession Planning | B11: Critical roles, incumbents, flight risk, up to 3 successors with readiness and development gaps.
A12: IDP Tracker | B12: Development goals and actions linked to talent outcomes, with status and progress tracking.
A13: Talent Dashboard | B13: KPI cards, 9-box distribution, flight risk, readiness, department averages, and charts for leadership reviews.
A15: Rating Scales
A16: Performance & Potential: 1 = Low / Below expectations · 2 = Partially meets · 3 = Meets expectations · 4 = Exceeds · 5 = Outstanding / Role model
A17: 9-Box labels: Star (H/H) · High Performer (H/M) · Solid Professional (H/L) · High Potential (M/H) · Core Player (M/M) · Inconsistent (M/L) · Rough Diamond (L/H) · Risk (L/M) · Underperformer (L/L)
A19: Color Convention
A20: Yellow cells + blue text | B20: Editable inputs (change these)
A21: Green / light blue cells | B21: Formulas — do not overwrite
A22: Red / Orange / Green fills on risk | B22: Conditional visual cues for risk and criticality
A24: Recommended Process
A25: 1. Managers complete Performance & Potential ratings and comments on Talent Review before the calibration meeting.
A26: 2. Calibration session: review 9-Box placements, challenge ratings, agree final positions.
A27: 3. Update Succession Planning for critical roles; identify gaps and development priorities.
A28: 4. Create or refresh IDPs for Stars, High Potentials, and anyone with material development needs.
A29: 5. Use Talent Dashboard in leadership reviews; track progress quarterly.

Sheet Talent Review
A1: TALENT REVIEW — Employee Assessment
A2: Cycle: FY2026 Q1 | Last Updated: 2026-09-29 | Instructions: Blue text = editable inputs. Use dropdowns where provided.
A4: Employee ID | B4: Employee Name | C4: Job Title | D4: Department | E4: Manager | F4: Hire Date | G4: Years in Role | H4: Performance Rating | I4: Potential Rating | J4: 9-Box Position | K4: Flight Risk | L4: Readiness for Promotion | M4: Key Strengths | N4: Development Areas | O4: Career Aspirations | P4: Retention Risk Notes | Q4: Last Review Date | R4: Reviewer
A5: E001 | B5: Amara Okonkwo | C5: Senior Software Engineer | D5: Engineering | E5: James Adeyemi | F5: 2019-03-15 | G5: 3.5 | H5: 4 | I5: 4 | J5: =IF(OR(H5="",I5=""),"",IF(AND(H5>=4,I5>=4),"Star",IF(AND(H5>=4,I5=3),"High Performer",IF(AND(H5>=4,I5<=2),"Solid Professional",IF(AND(H5=3,I5>=4),"High Potential",IF(AND(H5=3,I5=3),"Core Player",IF(AND(H5=3,I5<=2),"Inconsistent",IF(AND(H5<=2,I5>=4),"Rough Diamond",IF(AND(H5<=2,I5=3),"Risk","Underperformer"))))))))) -> Star | K5: Medium | L5: Ready in 1-2 years | M5: System design, mentoring, delivery | N5: Executive presence, stakeholder mgmt | O5: Engineering Manager | P5: Competitive offers in market | Q5: 2025-11-20 | R5: James Adeyemi
A6: E002 | B6: Chidi Nwosu | C6: Product Manager | D6: Product | E6: Sarah Bello | F6: 2020-07-01 | G6: 2 | H6: 5 | I6: 5 | J6: =IF(OR(H6="",I6=""),"",IF(AND(H6>=4,I6>=4),"Star",IF(AND(H6>=4,I6=3),"High Performer",IF(AND(H6>=4,I6<=2),"Solid Professional",IF(AND(H6=3,I6>=4),"High Potential",IF(AND(H6=3,I6=3),"Core Player",IF(AND(H6=3,I6<=2),"Inconsistent",IF(AND(H6<=2,I6>=4),"Rough Diamond",IF(AND(H6<=2,I6=3),"Risk","Underperformer"))))))))) -> Star | K6: Low | L6: Ready now | M6: Strategic thinking, customer empathy | N6: Technical depth | O6: Head of Product | P6: High performer, low risk | Q6: 2025-11-18 | R6: Sarah Bello
A7: E003 | B7: Fatima Ibrahim | C7: Finance Analyst | D7: Finance | E7: Tunde Bakare | F7: 2021-01-10 | G7: 1.5 | H7: 3 | I7: 3 | J7: =IF(OR(H7="",I7=""),"",IF(AND(H7>=4,I7>=4),"Star",IF(AND(H7>=4,I7=3),"High Performer",IF(AND(H7>=4,I7<=2),"Solid Professional",IF(AND(H7=3,I7>=4),"High Potential",IF(AND(H7=3,I7=3),"Core Player",IF(AND(H7=3,I7<=2),"Inconsistent",IF(AND(H7<=2,I7>=4),"Rough Diamond",IF(AND(H7<=2,I7=3),"Risk","Underperformer"))))))))) -> Core Player | K7: Low | L7: Ready in 2-3 years | M7: Attention to detail, Excel mastery | N7: Business partnering, storytelling | O7: FP&A Manager | Q7: 2025-11-22 | R7: Tunde Bakare
A8: E004 | B8: Kemi Adebayo | C8: HR Business Partner | D8: People | E8: Ngozi Eze | F8: 2018-05-20 | G8: 4 | H8: 4 | I8: 5 | J8: =IF(OR(H8="",I8=""),"",IF(AND(H8>=4,I8>=4),"Star",IF(AND(H8>=4,I8=3),"High Performer",IF(AND(H8>=4,I8<=2),"Solid Professional",IF(AND(H8=3,I8>=4),"High Potential",IF(AND(H8=3,I8=3),"Core Player",IF(AND(H8=3,I8<=2),"Inconsistent",IF(AND(H8<=2,I8>=4),"Rough Diamond",IF(AND(H8<=2,I8=3),"Risk","Underperformer"))))))))) -> Star | K8: Medium | L8: Ready in 1-2 years | M8: Coaching, talent processes | N8: Data analytics, change leadership | O8: Head of Talent | P8: Sought after externally | Q8: 2025-11-15 | R8: Ngozi Eze
A9: E005 | B9: Oluwaseun Ojo | C9: Sales Lead | D9: Sales | E9: Ibrahim Musa | F9: 2017-09-01 | G9: 5 | H9: 4 | I9: 3 | J9: =IF(OR(H9="",I9=""),"",IF(AND(H9>=4,I9>=4),"Star",IF(AND(H9>=4,I9=3),"High Performer",IF(AND(H9>=4,I9<=2),"Solid Professional",IF(AND(H9=3,I9>=4),"High Potential",IF(AND(H9=3,I9=3),"Core Player",IF(AND(H9=3,I9<=2),"Inconsistent",IF(AND(H9<=2,I9>=4),"Rough Diamond",IF(AND(H9<=2,I9=3),"Risk","Underperformer"))))))))) -> High Performer | K9: High | L9: Ready in 2-3 years | M9: Client relationships, closing | N9: Strategic account planning | O9: Regional Sales Director | P9: Has expressed interest in leaving | Q9: 2025-11-25 | R9: Ibrahim Musa
A10: E006 | B10: Blessing Eze | C10: Data Scientist | D10: Analytics | E10: James Adeyemi | F10: 2022-02-14 | G10: 1 | H10: 5 | I10: 4 | J10: =IF(OR(H10="",I10=""),"",IF(AND(H10>=4,I10>=4),"Star",IF(AND(H10>=4,I10=3),"High Performer",IF(AND(H10>=4,I10<=2),"Solid Professional",IF(AND(H10=3,I10>=4),"High Potential",IF(AND(H10=3,I10=3),"Core Player",IF(AND(H10=3,I10<=2),"Inconsistent",IF(AND(H10<=2,I10>=4),"Rough Diamond",IF(AND(H10<=2,I10=3),"Risk","Underperformer"))))))))) -> Star | K10: Low | L10: Ready in 1-2 years | M10: ML models, experimentation | N10: Business communication | O10: Lead Data Scientist | Q10: 2025-11-19 | R10: James Adeyemi
A11: E007 | B11: David Okoro | C11: Operations Manager | D11: Operations | E11: Grace Okonkwo | F11: 2016-11-30 | G11: 6 | H11: 3 | I11: 2 | J11: =IF(OR(H11="",I11=""),"",IF(AND(H11>=4,I11>=4),"Star",IF(AND(H11>=4,I11=3),"High Performer",IF(AND(H11>=4,I11<=2),"Solid Professional",IF(AND(H11=3,I11>=4),"High Potential",IF(AND(H11=3,I11=3),"Core Player",IF(AND(H11=3,I11<=2),"Inconsistent",IF(AND(H11<=2,I11>=4),"Rough Diamond",IF(AND(H11<=2,I11=3),"Risk","Underperformer"))))))))) -> Inconsistent | K11: Medium | L11: Not ready | M11: Process discipline, team leadership | N11: Innovation, digital fluency | O11: Stay in role / lateral | P11: Long tenure, may seek change | Q11: 2025-11-21 | R11: Grace Okonkwo
A12: E008 | B12: Aisha Mohammed | C12: Marketing Manager | D12: Marketing | E12: Sarah Bello | F12: 2019-08-12 | G12: 3 | H12: 4 | I12: 4 | J12: =IF(OR(H12="",I12=""),"",IF(AND(H12>=4,I12>=4),"Star",IF(AND(H12>=4,I12=3),"High Performer",IF(AND(H12>=4,I12<=2),"Solid Professional",IF(AND(H12=3,I12>=4),"High Potential",IF(AND(H12=3,I12=3),"Core Player",IF(AND(H12=3,I12<=2),"Inconsistent",IF(AND(H12<=2,I12>=4),"Rough Diamond",IF(AND(H12<=2,I12=3),"Risk","Underperformer"))))))))) -> Star | K12: Low | L12: Ready in 1-2 years | M12: Brand strategy, campaigns | N12: ROI measurement, analytics | O12: Head of Marketing | Q12: 2025-11-17 | R12: Sarah Bello
A13: E009 | B13: Emeka Obi | C13: Legal Counsel | D13: Legal | E13: Ngozi Eze | F13: 2020-04-01 | G13: 2.5 | H13: 3 | I13: 3 | J13: =IF(OR(H13="",I13=""),"",IF(AND(H13>=4,I13>=4),"Star",IF(AND(H13>=4,I13=3),"High Performer",IF(AND(H13>=4,I13<=2),"Solid Professional",IF(AND(H13=3,I13>=4),"High Potential",IF(AND(H13=3,I13=3),"Core Player",IF(AND(H13=3,I13<=2),"Inconsistent",IF(AND(H13<=2,I13>=4),"Rough Diamond",IF(AND(H13<=2,I13=3),"Risk","Underperformer"))))))))) -> Core Player | K13: Low | L13: Ready in 2-3 years | M13: Contract review, compliance | N13: Commercial negotiation | O13: Senior Counsel | Q13: 2025-11-23 | R13: Ngozi Eze
A14: E010 | B14: Grace Okonkwo | C14: Head of Operations | D14: Operations | E14: CEO | F14: 2015-01-15 | G14: 8 | H14: 4 | I14: 4 | J14: =IF(OR(H14="",I14=""),"",IF(AND(H14>=4,I14>=4),"Star",IF(AND(H14>=4,I14=3),"High Performer",IF(AND(H14>=4,I14<=2),"Solid Professional",IF(AND(H14=3,I14>=4),"High Potential",IF(AND(H14=3,I14=3),"Core Player",IF(AND(H14=3,I14<=2),"Inconsistent",IF(AND(H14<=2,I14>=4),"Rough Diamond",IF(AND(H14<=2,I14=3),"Risk","Underperformer"))))))))) -> Star | K14: Low | L14: Ready now | M14: Cross-functional leadership, scaling | N14: Board-level communication | O14: COO track | P14: Critical role holder | Q14: 2025-11-10 | R14: CEO
A15: E011 | B15: Ibrahim Musa | C15: Head of Sales | D15: Sales | E15: CEO | F15: 2014-06-01 | G15: 9 | H15: 5 | I15: 3 | J15: =IF(OR(H15="",I15=""),"",IF(AND(H15>=4,I15>=4),"Star",IF(AND(H15>=4,I15=3),"High Performer",IF(AND(H15>=4,I15<=2),"Solid Professional",IF(AND(H15=3,I15>=4),"High Potential",IF(AND(H15=3,I15=3),"Core Player",IF(AND(H15=3,I15<=2),"Inconsistent",IF(AND(H15<=2,I15>=4),"Rough Diamond",IF(AND(H15<=2,I15=3),"Risk","Underperformer"))))))))) -> High Performer | K15: Medium | L15: Ready in 1-2 years | M15: Revenue growth, team building | N15: Strategic planning, digital sales | O15: Commercial Director | P15: High value, moderate flight risk | Q15: 2025-11-12 | R15: CEO
A16: E012 | B16: Ngozi Eze | C16: CHRO | D16: People | E16: CEO | F16: 2013-03-01 | G16: 10 | H16: 5 | I16: 4 | J16: =IF(OR(H16="",I16=""),"",IF(AND(H16>=4,I16>=4),"Star",IF(AND(H16>=4,I16=3),"High Performer",IF(AND(H16>=4,I16<=2),"Solid Professional",IF(AND(H16=3,I16>=4),"High Potential",IF(AND(H16=3,I16=3),"Core Player",IF(AND(H16=3,I16<=2),"Inconsistent",IF(AND(H16<=2,I16>=4),"Rough Diamond",IF(AND(H16<=2,I16=3),"Risk","Underperformer"))))))))) -> Star | K16: Low | L16: Ready now | M16: Org design, culture, talent strategy | N16: External market brand | O16: Continue as CHRO / Board | P16: Key executive | Q16: 2025-11-08 | R16: CEO
A18: Legend & Rating Scales
A19: Performance & Potential: 1 = Low | 2 = Below Expectations | 3 = Meets Expectations | 4 = Exceeds | 5 = Outstanding
A20: 9-Box: Auto-calculated from Performance × Potential. Stars = High Perf + High Pot. Underperformers = Low Perf + Low Pot.
A21: Yellow cells = editable inputs (blue text). Green cells = formulas (do not overwrite).

Sheet 9-Box Matrix
A1: 9-BOX TALENT MATRIX — Performance × Potential
A2: Employees are auto-placed from the Talent Review sheet. Update ratings there; this view refreshes via formulas.
B3: ← PERFORMANCE | F3: EMPLOYEES BY 9-BOX POSITION
A4: POTENTIAL → | B4: LOW POTENTIAL (1-2) | C4: MEDIUM POTENTIAL (3) | D4: HIGH POTENTIAL (4-5) | F4: 9-Box Position | G4: Employee Name | H4: Dept | I4: Perf | J4: Pot
A5: HIGH PERFORMANCE (4-5) | B5: SOLID PROFESSIONAL | C5: HIGH PERFORMER | D5: STAR | F5: ='Talent Review'!J5 -> Star | G5: ='Talent Review'!B5 -> Amara Okonkwo | H5: ='Talent Review'!D5 -> Engineering | I5: ='Talent Review'!H5 -> 4 | J5: ='Talent Review'!I5 -> 4
B6: =COUNTIF('Talent Review'!J:J,"SOLID PROFESSIONAL") -> 0 | C6: =COUNTIF('Talent Review'!J:J,"HIGH PERFORMER") -> 2 | D6: =COUNTIF('Talent Review'!J:J,"STAR") -> 7 | F6: ='Talent Review'!J6 -> Star | G6: ='Talent Review'!B6 -> Chidi Nwosu | H6: ='Talent Review'!D6 -> Product | I6: ='Talent Review'!H6 -> 5 | J6: ='Talent Review'!I6 -> 5
B7: (see list →) | C7: (see list →) | D7: (see list →) | F7: ='Talent Review'!J7 -> Core Player | G7: ='Talent Review'!B7 -> Fatima Ibrahim | H7: ='Talent Review'!D7 -> Finance | I7: ='Talent Review'!H7 -> 3 | J7: ='Talent Review'!I7 -> 3
F8: ='Talent Review'!J8 -> Star | G8: ='Talent Review'!B8 -> Kemi Adebayo | H8: ='Talent Review'!D8 -> People | I8: ='Talent Review'!H8 -> 4 | J8: ='Talent Review'!I8 -> 5
A9: MEDIUM PERFORMANCE (3) | B9: INCONSISTENT | C9: CORE PLAYER | D9: HIGH POTENTIAL | F9: ='Talent Review'!J9 -> High Performer | G9: ='Talent Review'!B9 -> Oluwaseun Ojo | H9: ='Talent Review'!D9 -> Sales | I9: ='Talent Review'!H9 -> 4 | J9: ='Talent Review'!I9 -> 3
B10: =COUNTIF('Talent Review'!J:J,"INCONSISTENT") -> 1 | C10: =COUNTIF('Talent Review'!J:J,"CORE PLAYER") -> 2 | D10: =COUNTIF('Talent Review'!J:J,"HIGH POTENTIAL") -> 0 | F10: ='Talent Review'!J10 -> Star | G10: ='Talent Review'!B10 -> Blessing Eze | H10: ='Talent Review'!D10 -> Analytics | I10: ='Talent Review'!H10 -> 5 | J10: ='Talent Review'!I10 -> 4
B11: (see list →) | C11: (see list →) | D11: (see list →) | F11: ='Talent Review'!J11 -> Inconsistent | G11: ='Talent Review'!B11 -> David Okoro | H11: ='Talent Review'!D11 -> Operations | I11: ='Talent Review'!H11 -> 3 | J11: ='Talent Review'!I11 -> 2
F12: ='Talent Review'!J12 -> Star | G12: ='Talent Review'!B12 -> Aisha Mohammed | H12: ='Talent Review'!D12 -> Marketing | I12: ='Talent Review'!H12 -> 4 | J12: ='Talent Review'!I12 -> 4
A13: LOW PERFORMANCE (1-2) | B13: UNDERPERFORMER | C13: RISK | D13: ROUGH DIAMOND | F13: ='Talent Review'!J13 -> Core Player | G13: ='Talent Review'!B13 -> Emeka Obi | H13: ='Talent Review'!D13 -> Legal | I13: ='Talent Review'!H13 -> 3 | J13: ='Talent Review'!I13 -> 3
B14: =COUNTIF('Talent Review'!J:J,"UNDERPERFORMER") -> 0 | C14: =COUNTIF('Talent Review'!J:J,"RISK") -> 0 | D14: =COUNTIF('Talent Review'!J:J,"ROUGH DIAMOND") -> 0 | F14: ='Talent Review'!J14 -> Star | G14: ='Talent Review'!B14 -> Grace Okonkwo | H14: ='Talent Review'!D14 -> Operations | I14: ='Talent Review'!H14 -> 4 | J14: ='Talent Review'!I14 -> 4
B15: (see list →) | C15: (see list →) | D15: (see list →) | F15: ='Talent Review'!J15 -> High Performer | G15: ='Talent Review'!B15 -> Ibrahim Musa | H15: ='Talent Review'!D15 -> Sales | I15: ='Talent Review'!H15 -> 5 | J15: ='Talent Review'!I15 -> 3
F16: ='Talent Review'!J16 -> Star | G16: ='Talent Review'!B16 -> Ngozi Eze | H16: ='Talent Review'!D16 -> People | I16: ='Talent Review'!H16 -> 5 | J16: ='Talent Review'!I16 -> 4
A18: How to use | F18: BOX DISTRIBUTION SUMMARY
A19: 1. Update Performance & Potential ratings on the Talent Review sheet (columns H & I). | F19: Position | G19: Count | H19: % of Total
A20: 2. 9-Box Position auto-calculates. This matrix and the lists update automatically. | F20: Star | G20: =COUNTIF('Talent Review'!J:J,"Star") -> 7 | H20: =IF(COUNTA('Talent Review'!J5:J100)=0,0,G20/COUNTA('Talent Review'!J5:J100)) -> 0.58333333
A21: 3. Stars & High Potentials → focus of succession & acceleration. Underperformers → PIPs or exits. | F21: High Performer | G21: =COUNTIF('Talent Review'!J:J,"High Performer") -> 2 | H21: =IF(COUNTA('Talent Review'!J5:J100)=0,0,G21/COUNTA('Talent Review'!J5:J100)) -> 0.16666667
F22: Solid Professional | G22: =COUNTIF('Talent Review'!J:J,"Solid Professional") -> 0 | H22: =IF(COUNTA('Talent Review'!J5:J100)=0,0,G22/COUNTA('Talent Review'!J5:J100)) -> 0
F23: High Potential | G23: =COUNTIF('Talent Review'!J:J,"High Potential") -> 0 | H23: =IF(COUNTA('Talent Review'!J5:J100)=0,0,G23/COUNTA('Talent Review'!J5:J100)) -> 0
F24: Core Player | G24: =COUNTIF('Talent Review'!J:J,"Core Player") -> 2 | H24: =IF(COUNTA('Talent Review'!J5:J100)=0,0,G24/COUNTA('Talent Review'!J5:J100)) -> 0.16666667
F25: Inconsistent | G25: =COUNTIF('Talent Review'!J:J,"Inconsistent") -> 1 | H25: =IF(COUNTA('Talent Review'!J5:J100)=0,0,G25/COUNTA('Talent Review'!J5:J100)) -> 0.083333333
F26: Rough Diamond | G26: =COUNTIF('Talent Review'!J:J,"Rough Diamond") -> 0 | H26: =IF(COUNTA('Talent Review'!J5:J100)=0,0,G26/COUNTA('Talent Review'!J5:J100)) -> 0
F27: Risk | G27: =COUNTIF('Talent Review'!J:J,"Risk") -> 0 | H27: =IF(COUNTA('Talent Review'!J5:J100)=0,0,G27/COUNTA('Talent Review'!J5:J100)) -> 0
F28: Underperformer | G28: =COUNTIF('Talent Review'!J:J,"Underperformer") -> 0 | H28: =IF(COUNTA('Talent Review'!J5:J100)=0,0,G28/COUNTA('Talent Review'!J5:J100)) -> 0
F29: Total Employees | G29: =COUNTA('Talent Review'!B5:B100) -> 12

Sheet Succession Planning
A1: SUCCESSION PLANNING — Critical Roles & Successors
A2: Identify critical roles, current incumbents, and ready-now / ready-soon successors. Link to Talent Review ratings.
A4: Critical Role | B4: Incumbent | C4: Incumbent Flight Risk | D4: Role Criticality | E4: Successor 1 Name | F4: Successor 1 Readiness | G4: Successor 1 Gap | H4: Successor 2 Name | I4: Successor 2 Readiness | J4: Successor 2 Gap | K4: Successor 3 Name | L4: Successor 3 Readiness | M4: Successor 3 Gap | N4: Development Priority / Notes
A5: Chief Executive Officer | B5: Current CEO | C5: Low | D5: Mission Critical | E5: Grace Okonkwo | F5: Ready in 1-2 years | G5: Board exposure, P&L ownership | H5: Ngozi Eze | I5: Ready in 2-3 years | J5: Commercial experience | N5: Accelerate Grace via special projects & board observer role
A6: Chief Human Resources Officer | B6: Ngozi Eze | C6: Low | D6: Mission Critical | E6: Kemi Adebayo | F6: Ready in 1-2 years | G6: Strategic HR, external brand | N6: Kemi is primary successor; expand scope to org design
A7: Head of Operations | B7: Grace Okonkwo | C7: Low | D7: High | E7: David Okoro | F7: Not ready | G7: Innovation, digital, strategic scope | H7: Amara Okonkwo | I7: Ready in 2-3 years | J7: Ops domain knowledge | N7: Consider external search as backup; develop David or lateral
A8: Head of Sales | B8: Ibrahim Musa | C8: Medium | D8: High | E8: Oluwaseun Ojo | F8: Ready in 2-3 years | G8: Strategic planning, digital channels | N8: High flight risk on incumbent — prioritize bench strength
A9: Head of Product | B9: Vacant / Interim | C9: N/A | D9: High | E9: Chidi Nwosu | F9: Ready now | G9: None material | H9: Aisha Mohammed | I9: Ready in 1-2 years | J9: Product domain | N9: Chidi is ready-now candidate for promotion
A10: Head of Engineering | B10: James Adeyemi | C10: Low | D10: High | E10: Amara Okonkwo | F10: Ready in 1-2 years | G10: People leadership at scale | H10: Blessing Eze | I10: Ready in 2-3 years | J10: Engineering management experience | N10: Amara is primary; pair with leadership coach
A11: Head of Finance / CFO track | B11: Tunde Bakare | C11: Low | D11: High | E11: Fatima Ibrahim | F11: Ready in 2-3 years | G11: Business partnering, leadership | N11: Build Fatima via stretch assignments and mentoring
A12: Head of Marketing | B12: Sarah Bello (interim) | C12: Low | D12: Medium | E12: Aisha Mohammed | F12: Ready in 1-2 years | G12: P&L / commercial acumen | N12: Formalize Aisha as successor; expand commercial exposure
A14: SUCCESSION COVERAGE METRICS
A15: Total Critical Roles | B15: =COUNTA(A5:A50) -> 14
A16: Roles with ≥1 Ready-Now Successor | B16: =COUNTIF(F5:F50,"Ready now")+COUNTIF(I5:I50,"Ready now")+COUNTIF(L5:L50,"Ready now") -> 1
A17: Roles with High/Medium Incumbent Flight Risk | B17: =COUNTIF(C5:C50,"High")+COUNTIF(C5:C50,"Medium") -> 1
A18: Mission Critical Roles | B18: =COUNTIF(D5:D50,"Mission Critical") -> 2
A20: Note: Coverage formulas are illustrative. Refine with exact ready-now logic per role as needed.

Sheet IDP Tracker
A1: INDIVIDUAL DEVELOPMENT PLAN (IDP) TRACKER
A2: Track development actions linked to talent outcomes. Update Status and Progress %. Link employees to Talent Review.
A4: IDP ID | B4: Employee Name | C4: Employee ID | D4: Development Goal | E4: Linked 9-Box / Reason | F4: Action / Activity | G4: Owner (Manager/Coach) | H4: Start Date | I4: Target Date | J4: Status | K4: Progress % | L4: Evidence / Notes
A5: IDP-001 | B5: Amara Okonkwo | C5: E001 | D5: Build executive presence & stakeholder influence | E5: Star — promotion readiness | F5: Executive coaching (external) + lead QBR presentation | G5: James Adeyemi | H5: 2026-01-15 | I5: 2026-06-30 | J5: In Progress | K5: 40 | L5: First coaching session completed; QBR scheduled Mar
A6: IDP-002 | B6: Chidi Nwosu | C6: E002 | D6: Deepen technical product knowledge | E6: Star — ready now | F6: Shadow engineering sprint + complete internal tech curriculum | G6: Sarah Bello | H6: 2026-01-10 | I6: 2026-04-30 | J6: In Progress | K6: 60 | L6: Completed 2 of 4 modules
A7: IDP-003 | B7: Kemi Adebayo | C7: E004 | D7: Strengthen people analytics & data storytelling | E7: High Potential — CHRO track | F7: Lead workforce planning dashboard project + Tableau training | G7: Ngozi Eze | H7: 2026-02-01 | I7: 2026-08-31 | J7: Not Started | K7: 0 | L7: Kickoff scheduled Feb
A8: IDP-004 | B8: Oluwaseun Ojo | C8: E005 | D8: Strategic account planning & digital sales | E8: High Performer — succession for Head of Sales | F8: Own strategic plan for top 3 accounts + digital sales pilot | G8: Ibrahim Musa | H8: 2026-01-20 | I8: 2026-07-31 | J8: In Progress | K8: 25 | L8: Account plans draft due Feb
A9: IDP-005 | B9: Blessing Eze | C9: E006 | D9: Business communication & stakeholder management | E9: Star — leadership track | F9: Present model insights to leadership team quarterly | G9: James Adeyemi | H9: 2026-01-05 | I9: 2026-12-31 | J9: In Progress | K9: 15 | L9: First presentation in Mar
A10: IDP-006 | B10: David Okoro | C10: E007 | D10: Digital fluency & process innovation | E10: Core/Inconsistent — performance uplift | F10: Lead automation pilot in ops + digital skills course | G10: Grace Okonkwo | H10: 2026-02-01 | I10: 2026-09-30 | J10: Not Started | K10: 0 | L10: Course enrollment pending
A11: IDP-007 | B11: Aisha Mohammed | C11: E008 | D11: Commercial / ROI acumen for Head of Marketing track | E11: High Potential | F11: Own campaign ROI dashboard + rotate 1 day/week with Sales | G11: Sarah Bello | H11: 2026-01-15 | I11: 2026-06-30 | J11: In Progress | K11: 35 | L11: Dashboard live; sales rotation started
A12: IDP-008 | B12: Fatima Ibrahim | C12: E003 | D12: Business partnering & financial storytelling | E12: Core Player — FP&A Manager path | F12: Partner with 1 business unit on monthly forecast narrative | G12: Tunde Bakare | H12: 2026-02-01 | I12: 2026-08-31 | J12: Not Started | K12: 0 | L12: BU assignment to be confirmed
A13: IDP-009 | B13: Grace Okonkwo | C13: E010 | D13: Board-level communication & enterprise P&L | E13: Star — CEO succession | F13: Board observer + lead cross-functional transformation program | G13: CEO | H13: 2025-10-01 | I13: 2026-09-30 | J13: In Progress | K13: 55 | L13: Attended 2 board sessions; transformation ongoing
A14: IDP-010 | B14: Ibrahim Musa | C14: E011 | D14: Strategic planning & digital sales transformation | E14: High Performer — Commercial Director track | F14: Own 3-year commercial strategy + digital channel P&L | G14: CEO | H14: 2026-01-01 | I14: 2026-12-31 | J14: In Progress | K14: 20 | L14: Strategy outline in progress
A16: IDP PORTFOLIO SUMMARY
A17: Total Active IDPs | B17: =COUNTA(A5:A100) -> 17
A18: In Progress | B18: =COUNTIF(J5:J100,"In Progress") -> 7
A19: Not Started | B19: =COUNTIF(J5:J100,"Not Started") -> 3
A20: Completed | B20: =COUNTIF(J5:J100,"Completed") -> 0
A21: At Risk | B21: =COUNTIF(J5:J100,"At Risk") -> 0
A22: Average Progress % | B22: =IFERROR(AVERAGE(K5:K100),0) -> 25

Sheet Talent Dashboard
A1: TALENT DASHBOARD — HRBP Metrics & Insights
A2: Live metrics pulled from Talent Review, 9-Box, Succession, and IDP sheets. Refresh after updating source data.
A4: Total Employees | B4: Stars | C4: High Potentials | D4: High Flight Risk | E4: Ready-Now Successors | F4: Active IDPs | G4: Avg IDP Progress
A5: =COUNTA('Talent Review'!B5:B100) -> 12 | B5: =COUNTIF('Talent Review'!J:J,"Star") -> 7 | C5: =COUNTIF('Talent Review'!J:J,"High Potential")+COUNTIF('Talent Review'!J:J,"Star") -> 7 | D5: =COUNTIF('Talent Review'!K:K,"High") -> 1 | E5: =COUNTIF('Succession Planning'!F:F,"Ready now")+COUNTIF('Succession Planning'!I:I,"Ready now")+COUNTIF('Succession Planning'!L:L,"Ready now") -> 1 | F5: =COUNTA('IDP Tracker'!A5:A100) -> 17 | G5: =IFERROR(AVERAGE('IDP Tracker'!K5:K100),0) -> 25
A7: 9-BOX DISTRIBUTION | E7: FLIGHT RISK BREAKDOWN
A8: Position | B8: Count | C8: % | E8: Risk Level | F8: Count | G8: %
A9: Star | B9: =COUNTIF('Talent Review'!J:J,"Star") -> 7 | C9: =IF($B$18=0,0,B9/$B$18) -> 0.58333333 | E9: Low | F9: =COUNTIF('Talent Review'!K:K,"Low") -> 7 | G9: =IF(COUNTA('Talent Review'!K5:K100)=0,0,F9/COUNTA('Talent Review'!K5:K100)) -> 0.58333333
A10: High Performer | B10: =COUNTIF('Talent Review'!J:J,"High Performer") -> 2 | C10: =IF($B$18=0,0,B10/$B$18) -> 0.16666667 | E10: Medium | F10: =COUNTIF('Talent Review'!K:K,"Medium") -> 4 | G10: =IF(COUNTA('Talent Review'!K5:K100)=0,0,F10/COUNTA('Talent Review'!K5:K100)) -> 0.33333333
A11: Solid Professional | B11: =COUNTIF('Talent Review'!J:J,"Solid Professional") -> 0 | C11: =IF($B$18=0,0,B11/$B$18) -> 0 | E11: High | F11: =COUNTIF('Talent Review'!K:K,"High") -> 1 | G11: =IF(COUNTA('Talent Review'!K5:K100)=0,0,F11/COUNTA('Talent Review'!K5:K100)) -> 0.083333333
A12: High Potential | B12: =COUNTIF('Talent Review'!J:J,"High Potential") -> 0 | C12: =IF($B$18=0,0,B12/$B$18) -> 0
A13: Core Player | B13: =COUNTIF('Talent Review'!J:J,"Core Player") -> 2 | C13: =IF($B$18=0,0,B13/$B$18) -> 0.16666667 | E13: PROMOTION READINESS
A14: Inconsistent | B14: =COUNTIF('Talent Review'!J:J,"Inconsistent") -> 1 | C14: =IF($B$18=0,0,B14/$B$18) -> 0.083333333 | E14: Readiness | F14: Count
A15: Rough Diamond | B15: =COUNTIF('Talent Review'!J:J,"Rough Diamond") -> 0 | C15: =IF($B$18=0,0,B15/$B$18) -> 0 | E15: Ready now | F15: =COUNTIF('Talent Review'!L:L,"Ready now") -> 3
A16: Risk | B16: =COUNTIF('Talent Review'!J:J,"Risk") -> 0 | C16: =IF($B$18=0,0,B16/$B$18) -> 0 | E16: Ready in 1-2 years | F16: =COUNTIF('Talent Review'!L:L,"Ready in 1-2 years") -> 5
A17: Underperformer | B17: =COUNTIF('Talent Review'!J:J,"Underperformer") -> 0 | C17: =IF($B$18=0,0,B17/$B$18) -> 0 | E17: Ready in 2-3 years | F17: =COUNTIF('Talent Review'!L:L,"Ready in 2-3 years") -> 3
A18: Total | B18: =SUM(B9:B17) -> 12 | E18: Not ready | F18: =COUNTIF('Talent Review'!L:L,"Not ready") -> 1
A20: HEADCOUNT BY DEPARTMENT
A21: Department | B21: Count | C21: Avg Perf | D21: Avg Pot
A22: Engineering | B22: =COUNTIF('Talent Review'!D:D,"Engineering") -> 1 | C22: =IFERROR(AVERAGEIF('Talent Review'!D:D,"Engineering",'Talent Review'!H:H),"-") -> 4 | D22: =IFERROR(AVERAGEIF('Talent Review'!D:D,"Engineering",'Talent Review'!I:I),"-") -> 4
A23: Product | B23: =COUNTIF('Talent Review'!D:D,"Product") -> 1 | C23: =IFERROR(AVERAGEIF('Talent Review'!D:D,"Product",'Talent Review'!H:H),"-") -> 5 | D23: =IFERROR(AVERAGEIF('Talent Review'!D:D,"Product",'Talent Review'!I:I),"-") -> 5
A24: Finance | B24: =COUNTIF('Talent Review'!D:D,"Finance") -> 1 | C24: =IFERROR(AVERAGEIF('Talent Review'!D:D,"Finance",'Talent Review'!H:H),"-") -> 3 | D24: =IFERROR(AVERAGEIF('Talent Review'!D:D,"Finance",'Talent Review'!I:I),"-") -> 3
A25: People | B25: =COUNTIF('Talent Review'!D:D,"People") -> 2 | C25: =IFERROR(AVERAGEIF('Talent Review'!D:D,"People",'Talent Review'!H:H),"-") -> 4.5 | D25: =IFERROR(AVERAGEIF('Talent Review'!D:D,"People",'Talent Review'!I:I),"-") -> 4.5
A26: Sales | B26: =COUNTIF('Talent Review'!D:D,"Sales") -> 2 | C26: =IFERROR(AVERAGEIF('Talent Review'!D:D,"Sales",'Talent Review'!H:H),"-") -> 4.5 | D26: =IFERROR(AVERAGEIF('Talent Review'!D:D,"Sales",'Talent Review'!I:I),"-") -> 3
A27: Analytics | B27: =COUNTIF('Talent Review'!D:D,"Analytics") -> 1 | C27: =IFERROR(AVERAGEIF('Talent Review'!D:D,"Analytics",'Talent Review'!H:H),"-") -> 5 | D27: =IFERROR(AVERAGEIF('Talent Review'!D:D,"Analytics",'Talent Review'!I:I),"-") -> 4
A28: Operations | B28: =COUNTIF('Talent Review'!D:D,"Operations") -> 2 | C28: =IFERROR(AVERAGEIF('Talent Review'!D:D,"Operations",'Talent Review'!H:H),"-") -> 3.5 | D28: =IFERROR(AVERAGEIF('Talent Review'!D:D,"Operations",'Talent Review'!I:I),"-") -> 3
A29: Marketing | B29: =COUNTIF('Talent Review'!D:D,"Marketing") -> 1 | C29: =IFERROR(AVERAGEIF('Talent Review'!D:D,"Marketing",'Talent Review'!H:H),"-") -> 4 | D29: =IFERROR(AVERAGEIF('Talent Review'!D:D,"Marketing",'Talent Review'!I:I),"-") -> 4
A30: Legal | B30: =COUNTIF('Talent Review'!D:D,"Legal") -> 1 | C30: =IFERROR(AVERAGEIF('Talent Review'!D:D,"Legal",'Talent Review'!H:H),"-") -> 3 | D30: =IFERROR(AVERAGEIF('Talent Review'!D:D,"Legal",'Talent Review'!I:I),"-") -> 3
A32: HOW TO USE THIS WORKBOOK
A33: 1. Start on Talent Review: enter/update employee ratings (Performance & Potential are yellow input cells with dropdowns).
A34: 2. 9-Box Position calculates automatically. Review the 9-Box Matrix sheet for visual placement and distribution.
A35: 3. Maintain Succession Planning for critical roles — flag flight risk and name successors with readiness.
A36: 4. Log development actions on IDP Tracker and update Status + Progress % regularly.
A37: 5. Talent Dashboard aggregates KPIs and charts for HRBP / leadership reviews. All metrics are formula-driven.
